README.rst
logstash_index_cleaner.py
setup.py
logstash_index_cleaner.egg-info/PKG-INFO
logstash_index_cleaner.egg-info/SOURCES.txt
logstash_index_cleaner.egg-info/dependency_links.txt
logstash_index_cleaner.egg-info/entry_points.txt
logstash_index_cleaner.egg-info/not-zip-safe
logstash_index_cleaner.egg-info/requires.txt
logstash_index_cleaner.egg-info/top_level.txt