Metadata-Version: 1.1
Name: logstash-index-cleaner
Version: 0.2.2
Summary: Delete old logstash indices from Elasticsearch
Home-page: https://github.com/Yipit/logstash-index-cleaner
Author: Yipit Coders
Author-email: coders@yipit.com
License: UNKNOWN
Platform: UNKNOWN
Classifier: Programming Language :: Python
